brokelink/__init__.py
brokelink/cli.py
brokelink/parser.py
brokelink/utils.py
brokelink-0.1.0.dist-info/LICENSE
brokelink-0.1.0.dist-info/METADATA
brokelink-0.1.0.dist-info/WHEEL
brokelink-0.1.0.dist-info/entry_points.txt
brokelink-0.1.0.dist-info/top_level.txt
brokelink-0.1.0.dist-info/RECORD
