Metadata-Version: 2.1
Name: brokelink
Version: 0.1.0
Summary: Dead link scanner for .md and .html docs
Home-page: https://github.com/000xs/brokelink
Author: Sithum Sathsara Rajapakshe | 000x
License: MIT
Classifier: Programming Language :: Python :: 3
Classifier: License :: OSI Approved :: MIT License
Classifier: Operating System :: Unix
Requires-Python: >=3.7
License-File: LICENSE
